{
  "name": "vkReleasePerformanceConfigurationINTEL",
  "returnType": "VkResult",
  "signature": "VkResult vkReleasePerformanceConfigurationINTEL(\n VkDevice device,\n VkPerformanceConfigurationINTEL configuration);",
  "description": "الوصف الرسمي: دالة مرجعية من Vulkan. الشرح التفصيلي الكامل غير متوفر محلياً بعد، لذا أُضيف لها وصف عملي مختصر.",
  "usage": [
    "تُستخدم هذه الدالة من أجل: تحرير a configuration to capture performance data..",
    "بعد الاستدعاء افحص القيمة المرجعة وتعامل مع حالات النجاح أو الخطأ المناسبة قبل متابعة التنفيذ."
  ],
  "parameters": [
    {
      "name": "device",
      "type": "VkDevice",
      "description": "الجهاز المنطقي الذي ستُنفذ عليه هذه العملية."
    },
    {
      "name": "configuration",
      "type": "VkPerformanceConfigurationINTEL",
      "description": "معامل من النوع VkPerformanceConfigurationINTEL تستخدمه الدالة ضمن هذه العملية."
    }
  ],
  "returnValues": [
    {
      "value": "VK_SUCCESS",
      "description": "تم تنفيذ العملية بنجاح."
    },
    {
      "value": "VK_ERROR_OUT_OF_HOST_MEMORY",
      "description": "فشل بسبب نفاد ذاكرة المضيف."
    },
    {
      "value": "VK_ERROR_TOO_MANY_OBJECTS",
      "description": "تم تجاوز الحد المسموح من الكائنات."
    },
    {
      "value": "VK_ERROR_UNKNOWN",
      "description": "حدث خطأ غير محدد من تعريف Vulkan أو المنصة."
    },
    {
      "value": "VK_ERROR_VALIDATION_FAILED",
      "description": "فشلت التحققّات القياسية الخاصة بصحة الاستخدام."
    }
  ],
  "notes": [
    "تتطلب هذه الدالة توفر الامتداد أو الميزة: VK_INTEL_performance_query."
  ],
  "example": "",
  "seeAlso": [
    "VkDevice",
    "VkPerformanceConfigurationINTEL"
  ],
  "parserVersion": 3
}