{
  "schemaVersion": "2026-03-reference-architecture-1",
  "library": {
    "id": "vulkan",
    "displayName": "Vulkan",
    "displayNameArabic": "فولكان",
    "description": "طبقة المرجع العربية لعناصر Vulkan منخفضة المستوى: الدوال والبنى والتعدادات والثوابت والأنواع."
  },
  "kind": {
    "id": "functions",
    "displayName": "Functions",
    "displayNameArabic": "الدوال",
    "description": "استدعاءات تنفذ فعلاً، تغيّر حالة، أو تعيد نتيجة، أو تبني مورداً."
  },
  "identity": {
    "name": "vkCmdInsertDebugUtilsLabelEXT",
    "slug": "vk-cmd-insert-debug-utils-label-ext",
    "titleArabic": "أمر يُسجَّل لإدراج وسم تصحيحي في الموضع الحالي داخل مخزن الأوامر",
    "aliases": []
  },
  "route": {
    "hash": "#ref/vulkan/functions/vk-cmd-insert-debug-utils-label-ext",
    "contentPath": "content/reference/vulkan/functions/vk-cmd-insert-debug-utils-label-ext.json"
  },
  "summary": {
    "actualTranslationArabic": "أمر يُسجَّل لإدراج وسم تصحيحي في الموضع الحالي داخل مخزن الأوامر",
    "actualMeaningArabic": "أمر يُسجَّل لإدراج وسم تصحيحي في الموضع الحالي داخل مخزن الأوامر",
    "purposeArabic": "المعنى الأساسي لهذه الدالة: أمر يُسجَّل لإدراج وسم تصحيحي في الموضع الحالي داخل مخزن الأوامر.",
    "whyUseArabic": "تُستخدم لإدراج وسم تصحيحي في الموضع الحالي داخل مخزن الأوامر من دون فتح نطاق جديد.",
    "carriedValueArabic": "القيمة العملية لهذا الاستدعاء تظهر في ناتجه void وفي التغيير الذي يحدثه على المورد أو الحالة المرتبطة به.",
    "sourceDescription": "الوصف الرسمي: أمر يُسجَّل لإدراج وسم تصحيحي في الموضع الحالي داخل مخزن الأوامر"
  },
  "signature": {
    "raw": "void vkCmdInsertDebugUtilsLabelEXT(\n VkCommandBuffer commandBuffer,\n const VkDebugUtilsLabelEXT* pLabelInfo);",
    "returnType": "void",
    "parameters": [
      "VkCommandBuffer commandBuffer",
      "const VkDebugUtilsLabelEXT* pLabelInfo"
    ],
    "header": "",
    "headerUrl": ""
  },
  "details": {
    "parameters": [
      {
        "name": "commandBuffer",
        "type": "VkCommandBuffer",
        "descriptionArabic": "يمثل المقبض VkCommandBuffer الذي يحدد مخزن الأوامر الذي ستُسجَّل داخله الأوامر قبل أن يقرأها المعالج الرسومي لاحقًا.",
        "originalDescription": "يمثل المقبض VkCommandBuffer الذي يحدد مخزن الأوامر الذي ستُسجَّل داخله الأوامر قبل أن يقرأها المعالج الرسومي لاحقًا."
      },
      {
        "name": "pLabelInfo",
        "type": "const VkDebugUtilsLabelEXT*",
        "descriptionArabic": "يمثل عنوان بيانات إدخال من النوع VkDebugUtilsLabelEXT تقرأها Vulkan أثناء تنفيذ هذا الاستدعاء",
        "originalDescription": "يمثل عنوان بيانات إدخال من النوع VkDebugUtilsLabelEXT تقرأها Vulkan أثناء تنفيذ هذا الاستدعاء"
      }
    ],
    "fields": [],
    "values": [],
    "usage": [
      "المعنى الأساسي لهذه الدالة: أمر يُسجَّل لإدراج وسم تصحيحي في الموضع الحالي داخل مخزن الأوامر.",
      "تُستخدم لإدراج وسم تصحيحي في الموضع الحالي داخل مخزن الأوامر من دون فتح نطاق جديد.",
      "هذا يفيد لإضافة نقطة مرجعية سريعة داخل تسلسل الأوامر، بحيث تظهر في أدوات التصحيح كعلامة على حدث أو مرحلة محددة.",
      "هذه الدالة مرتبطة بالامتداد EXT أو إحدى صيغ الامتداد الخاصة به، لذلك يجب التأكد من دعم الامتداد وتفعيله قبل الاستخدام.",
      "لا تعيد هذه الدالة قيمة مباشرة، ويظهر أثرها على الحالة أو المورد الذي تمرره إليها."
    ],
    "notes": [
      "تتطلب هذه الدالة توفر الامتداد أو الميزة: VK_EXT_debug_utils."
    ],
    "remarks": [],
    "instructions": [],
    "lifecycle": [],
    "returns": "",
    "threadSafety": "",
    "example": "VkCommandBuffer commandBuffer = VK_NULL_HANDLE;\nVkDebugUtilsLabelEXT* labelInfo = nullptr;\n\nvkCmdInsertDebugUtilsLabelEXT(\n commandBuffer,\n labelInfo\n);"
  },
  "links": {
    "officialUrl": "https://docs.vulkan.org/refpages/latest/refpages/source/vkCmdInsertDebugUtilsLabelEXT.html",
    "sourceUrl": "",
    "related": [
      {
        "name": "VkCommandBuffer",
        "route": "#ref/vulkan/variables/vk-command-buffer",
        "libraryId": "vulkan",
        "kindId": "variables"
      },
      {
        "name": "VkDebugUtilsLabelEXT",
        "route": "#ref/vulkan/structures/vk-debug-utils-label-ext",
        "libraryId": "vulkan",
        "kindId": "structures"
      }
    ]
  },
  "source": {
    "dataset": "data/vulkan_site_data.json",
    "category": "مخزن الأوامر",
    "packageKey": "",
    "packageName": ""
  }
}
