{
  "schemaVersion": "2026-03-reference-architecture-1",
  "library": {
    "id": "sdl3-core",
    "displayName": "SDL3 API",
    "displayNameArabic": "SDL3",
    "description": "النواة الأساسية لـ SDL3: النوافذ، الإدخال، الأحداث، الصوت، والرسم الأساسي."
  },
  "kind": {
    "id": "functions",
    "displayName": "Functions",
    "displayNameArabic": "الدوال",
    "description": "استدعاءات تنفذ فعلاً، تغيّر حالة، أو تعيد نتيجة، أو تبني مورداً."
  },
  "identity": {
    "name": "SDL_UploadToGPUBuffer",
    "slug": "sdl-upload-to-gpu-buffer",
    "titleArabic": "Uploads data from a transfer buffer to a buffer",
    "aliases": []
  },
  "route": {
    "hash": "#ref/sdl3-core/functions/sdl-upload-to-gpu-buffer",
    "contentPath": "content/reference/sdl3-core/functions/sdl-upload-to-gpu-buffer.json"
  },
  "summary": {
    "actualTranslationArabic": "Uploads data from a transfer buffer to a buffer",
    "actualMeaningArabic": "تمثل هذه الدالة عملية تشغيل SDL Upload To GPU المخزن داخل SDL3، وتنفذ فعلاً عند استدعائها لا مجرد تعريف نظري.",
    "purposeArabic": "تستخدم هذه الدالة عندما تحتاج إلى تشغيل SDL Upload To GPU المخزن داخل التطبيق أو داخل مسار التنفيذ المرتبط بها.",
    "whyUseArabic": "القيمة الحقيقية هنا هي الأثر التنفيذي الذي يحدثه الاستدعاء أو النتيجة التي يعيدها إلى التطبيق.",
    "carriedValueArabic": "القيمة العملية لهذا الاستدعاء تظهر في ناتجه void وفي التغيير الذي يحدثه على المورد أو الحالة المرتبطة به.",
    "sourceDescription": "Uploads data from a transfer buffer to a buffer."
  },
  "signature": {
    "raw": "void SDL_UploadToGPUBuffer(\n SDL_GPUCopyPass *copy_pass,\n const SDL_GPUTransferBufferLocation *source,\n const SDL_GPUBufferRegion *destination,\n bool cycle);",
    "returnType": "void",
    "parameters": [
      "SDL_GPUCopyPass *copy_pass",
      "const SDL_GPUTransferBufferLocation *source",
      "const SDL_GPUBufferRegion *destination",
      "bool cycle"
    ],
    "header": "",
    "headerUrl": "https://github.com/libsdl-org/SDL/blob/main/include/SDL3/SDL_gpu.h"
  },
  "details": {
    "parameters": [
      {
        "name": "copy_pass",
        "type": "SDL_GPUCopyPass *",
        "descriptionArabic": "يمثل المعامل copy_pass من النوع SDL_GPUCopyPass * القيمة أو المورد الذي يعتمد عليه هذا الاستدعاء.",
        "originalDescription": "a copy pass handle."
      },
      {
        "name": "source",
        "type": "const SDL_GPUTransferBufferLocation\n*",
        "descriptionArabic": "يمثل المعامل source من النوع const SDL_GPUTransferBufferLocation\n* القيمة أو المورد الذي يعتمد عليه هذا الاستدعاء.",
        "originalDescription": "the source transfer buffer with offset."
      },
      {
        "name": "destination",
        "type": "const SDL_GPUBufferRegion\n*",
        "descriptionArabic": "يمثل المعامل destination من النوع const SDL_GPUBufferRegion\n* القيمة أو المورد الذي يعتمد عليه هذا الاستدعاء.",
        "originalDescription": "the destination buffer with offset and size."
      },
      {
        "name": "cycle",
        "type": "bool",
        "descriptionArabic": "يمثل المعامل cycle من النوع bool القيمة أو المورد الذي يعتمد عليه هذا الاستدعاء.",
        "originalDescription": "if true, cycles the buffer if it is already bound, otherwise\noverwrites the data."
      }
    ],
    "fields": [],
    "values": [],
    "usage": [
      "هذا العنصر متاح منذ SDL 3.2.0."
    ],
    "notes": [],
    "remarks": [
      "The upload occurs on the GPU timeline. You may assume that the upload\nhas finished in subsequent commands."
    ],
    "instructions": [],
    "lifecycle": [],
    "returns": "",
    "threadSafety": "",
    "example": ""
  },
  "links": {
    "officialUrl": "https://wiki.libsdl.org/SDL3/SDL_UploadToGPUBuffer",
    "sourceUrl": "",
    "related": []
  },
  "source": {
    "dataset": "data/ui/sdl3.json",
    "category": "3D Rendering and GPU Compute",
    "packageKey": "core",
    "packageName": "SDL3"
  }
}
