{"fileName":"vk_safe_struct.hpp","index":0,"startLine":1,"endLine":450,"lineCount":450,"content":"// *** THIS FILE IS GENERATED - DO NOT EDIT ***\n// See safe_struct_generator.py for modifications\n\n/***************************************************************************\n *\n * Copyright (c) 2015-2025 The Khronos Group Inc.\n * Copyright (c) 2015-2025 Valve Corporation\n * Copyright (c) 2015-2025 LunarG, Inc.\n * Copyright (c) 2015-2025 Google Inc.\n *\n * SPDX-License-Identifier: Apache-2.0\n *\n ****************************************************************************/\n\n// NOLINTBEGIN\n\n#pragma once\n#include <vulkan/vulkan.h>\n#include <algorithm>\n\n#include <vulkan/utility/vk_safe_struct_utils.hpp>\n\nnamespace vku {\n\n// Mapping of unknown stype codes to structure lengths. This should be set up by the application\n// before vkCreateInstance() and not modified afterwards.\nstd::vector<std::pair<uint32_t, uint32_t>>& GetCustomStypeInfo();\n\nstruct safe_VkBufferMemoryBarrier {\n    VkStructureType sType;\n    const void* pNext{};\n    VkAccessFlags srcAccessMask;\n    VkAccessFlags dstAccessMask;\n    uint32_t srcQueueFamilyIndex;\n    uint32_t dstQueueFamilyIndex;\n    VkBuffer buffer;\n    VkDeviceSize offset;\n    VkDeviceSize size;\n\n    safe_VkBufferMemoryBarrier(const VkBufferMemoryBarrier* in_struct, PNextCopyState* copy_state = {}, bool copy_pnext = true);\n    safe_VkBufferMemoryBarrier(const safe_VkBufferMemoryBarrier& copy_src);\n    safe_VkBufferMemoryBarrier& operator=(const safe_VkBufferMemoryBarrier& copy_src);\n    safe_VkBufferMemoryBarrier();\n    ~safe_VkBufferMemoryBarrier();\n    void initialize(const VkBufferMemoryBarrier* in_struct, PNextCopyState* copy_state = {});\n    void initialize(const safe_VkBufferMemoryBarrier* copy_src, PNextCopyState* copy_state = {});\n    VkBufferMemoryBarrier* ptr() { return reinterpret_cast<VkBufferMemoryBarrier*>(this); }\n    VkBufferMemoryBarrier const* ptr() const { return reinterpret_cast<VkBufferMemoryBarrier const*>(this); }\n};\nstruct safe_VkImageMemoryBarrier {\n    VkStructureType sType;\n    const void* pNext{};\n    VkAccessFlags srcAccessMask;\n    VkAccessFlags dstAccessMask;\n    VkImageLayout oldLayout;\n    VkImageLayout newLayout;\n    uint32_t srcQueueFamilyIndex;\n    uint32_t dstQueueFamilyIndex;\n    VkImage image;\n    VkImageSubresourceRange subresourceRange;\n\n    safe_VkImageMemoryBarrier(const VkImageMemoryBarrier* in_struct, PNextCopyState* copy_state = {}, bool copy_pnext = true);\n    safe_VkImageMemoryBarrier(const safe_VkImageMemoryBarrier& copy_src);\n    safe_VkImageMemoryBarrier& operator=(const safe_VkImageMemoryBarrier& copy_src);\n    safe_VkImageMemoryBarrier();\n    ~safe_VkImageMemoryBarrier();\n    void initialize(const VkImageMemoryBarrier* in_struct, PNextCopyState* copy_state = {});\n    void initialize(const safe_VkImageMemoryBarrier* copy_src, PNextCopyState* copy_state = {});\n    VkImageMemoryBarrier* ptr() { return reinterpret_cast<VkImageMemoryBarrier*>(this); }\n    VkImageMemoryBarrier const* ptr() const { return reinterpret_cast<VkImageMemoryBarrier const*>(this); }\n};\nstruct safe_VkMemoryBarrier {\n    VkStructureType sType;\n    const void* pNext{};\n    VkAccessFlags srcAccessMask;\n    VkAccessFlags dstAccessMask;\n\n    safe_VkMemoryBarrier(const VkMemoryBarrier* in_struct, PNextCopyState* copy_state = {}, bool copy_pnext = true);\n    safe_VkMemoryBarrier(const safe_VkMemoryBarrier& copy_src);\n    safe_VkMemoryBarrier& operator=(const safe_VkMemoryBarrier& copy_src);\n    safe_VkMemoryBarrier();\n    ~safe_VkMemoryBarrier();\n    void initialize(const VkMemoryBarrier* in_struct, PNextCopyState* copy_state = {});\n    void initialize(const safe_VkMemoryBarrier* copy_src, PNextCopyState* copy_state = {});\n    VkMemoryBarrier* ptr() { return reinterpret_cast<VkMemoryBarrier*>(this); }\n    VkMemoryBarrier const* ptr() const { return reinterpret_cast<VkMemoryBarrier const*>(this); }\n};\nstruct safe_VkAllocationCallbacks {\n    void* pUserData{};\n    PFN_vkAllocationFunction pfnAllocation;\n    PFN_vkReallocationFunction pfnReallocation;\n    PFN_vkFreeFunction pfnFree;\n    PFN_vkInternalAllocationNotification pfnInternalAllocation;\n    PFN_vkInternalFreeNotification pfnInternalFree;\n\n    safe_VkAllocationCallbacks(const VkAllocationCallbacks* in_struct, PNextCopyState* copy_state = {});\n    safe_VkAllocationCallbacks(const safe_VkAllocationCallbacks& copy_src);\n    safe_VkAllocationCallbacks& operator=(const safe_VkAllocationCallbacks& copy_src);\n    safe_VkAllocationCallbacks();\n    ~safe_VkAllocationCallbacks();\n    void initialize(const VkAllocationCallbacks* in_struct, PNextCopyState* copy_state = {});\n    void initialize(const safe_VkAllocationCallbacks* copy_src, PNextCopyState* copy_state = {});\n    VkAllocationCallbacks* ptr() { return reinterpret_cast<VkAllocationCallbacks*>(this); }\n    VkAllocationCallbacks const* ptr() const { return reinterpret_cast<VkAllocationCallbacks const*>(this); }\n};\nstruct safe_VkApplicationInfo {\n    VkStructureType sType;\n    const void* pNext{};\n    const char* pApplicationName{};\n    uint32_t applicationVersion;\n    const char* pEngineName{};\n    uint32_t engineVersion;\n    uint32_t apiVersion;\n\n    safe_VkApplicationInfo(const VkApplicationInfo* in_struct, PNextCopyState* copy_state = {}, bool copy_pnext = true);\n    safe_VkApplicationInfo(const safe_VkApplicationInfo& copy_src);\n    safe_VkApplicationInfo& operator=(const safe_VkApplicationInfo& copy_src);\n    safe_VkApplicationInfo();\n    ~safe_VkApplicationInfo();\n    void initialize(const VkApplicationInfo* in_struct, PNextCopyState* copy_state = {});\n    void initialize(const safe_VkApplicationInfo* copy_src, PNextCopyState* copy_state = {});\n    VkApplicationInfo* ptr() { return reinterpret_cast<VkApplicationInfo*>(this); }\n    VkApplicationInfo const* ptr() const { return reinterpret_cast<VkApplicationInfo const*>(this); }\n};\nstruct safe_VkInstanceCreateInfo {\n    VkStructureType sType;\n    const void* pNext{};\n    VkInstanceCreateFlags flags;\n    safe_VkApplicationInfo* pApplicationInfo{};\n    uint32_t enabledLayerCount;\n    const char* const* ppEnabledLayerNames{};\n    uint32_t enabledExtensionCount;\n    const char* const* ppEnabledExtensionNames{};\n\n    safe_VkInstanceCreateInfo(const VkInstanceCreateInfo* in_struct, PNextCopyState* copy_state = {}, bool copy_pnext = true);\n    safe_VkInstanceCreateInfo(const safe_VkInstanceCreateInfo& copy_src);\n    safe_VkInstanceCreateInfo& operator=(const safe_VkInstanceCreateInfo& copy_src);\n    safe_VkInstanceCreateInfo();\n    ~safe_VkInstanceCreateInfo();\n    void initialize(const VkInstanceCreateInfo* in_struct, PNextCopyState* copy_state = {});\n    void initialize(const safe_VkInstanceCreateInfo* copy_src, PNextCopyState* copy_state = {});\n    VkInstanceCreateInfo* ptr() { return reinterpret_cast<VkInstanceCreateInfo*>(this); }\n    VkInstanceCreateInfo const* ptr() const { return reinterpret_cast<VkInstanceCreateInfo const*>(this); }\n};\nstruct safe_VkDeviceQueueCreateInfo {\n    VkStructureType sType;\n    const void* pNext{};\n    VkDeviceQueueCreateFlags flags;\n    uint32_t queueFamilyIndex;\n    uint32_t queueCount;\n    const float* pQueuePriorities{};\n\n    safe_VkDeviceQueueCreateInfo(const VkDeviceQueueCreateInfo* in_struct, PNextCopyState* copy_state = {}, bool copy_pnext = true);\n    safe_VkDeviceQueueCreateInfo(const safe_VkDeviceQueueCreateInfo& copy_src);\n    safe_VkDeviceQueueCreateInfo& operator=(const safe_VkDeviceQueueCreateInfo& copy_src);\n    safe_VkDeviceQueueCreateInfo();\n    ~safe_VkDeviceQueueCreateInfo();\n    void initialize(const VkDeviceQueueCreateInfo* in_struct, PNextCopyState* copy_state = {});\n    void initialize(const safe_VkDeviceQueueCreateInfo* copy_src, PNextCopyState* copy_state = {});\n    VkDeviceQueueCreateInfo* ptr() { return reinterpret_cast<VkDeviceQueueCreateInfo*>(this); }\n    VkDeviceQueueCreateInfo const* ptr() const { return reinterpret_cast<VkDeviceQueueCreateInfo const*>(this); }\n};\nstruct safe_VkDeviceCreateInfo {\n    VkStructureType sType;\n    const void* pNext{};\n    VkDeviceCreateFlags flags;\n    uint32_t queueCreateInfoCount;\n    safe_VkDeviceQueueCreateInfo* pQueueCreateInfos{};\n    uint32_t enabledLayerCount;\n    const char* const* ppEnabledLayerNames{};\n    uint32_t enabledExtensionCount;\n    const char* const* ppEnabledExtensionNames{};\n    const VkPhysicalDeviceFeatures* pEnabledFeatures{};\n\n    safe_VkDeviceCreateInfo(const VkDeviceCreateInfo* in_struct, PNextCopyState* copy_state = {}, bool copy_pnext = true);\n    safe_VkDeviceCreateInfo(const safe_VkDeviceCreateInfo& copy_src);\n    safe_VkDeviceCreateInfo& operator=(const safe_VkDeviceCreateInfo& copy_src);\n    safe_VkDeviceCreateInfo();\n    ~safe_VkDeviceCreateInfo();\n    void initialize(const VkDeviceCreateInfo* in_struct, PNextCopyState* copy_state = {});\n    void initialize(const safe_VkDeviceCreateInfo* copy_src, PNextCopyState* copy_state = {});\n    VkDeviceCreateInfo* ptr() { return reinterpret_cast<VkDeviceCreateInfo*>(this); }\n    VkDeviceCreateInfo const* ptr() const { return reinterpret_cast<VkDeviceCreateInfo const*>(this); }\n};\nstruct safe_VkSubmitInfo {\n    VkStructureType sType;\n    const void* pNext{};\n    uint32_t waitSemaphoreCount;\n    VkSemaphore* pWaitSemaphores{};\n    const VkPipelineStageFlags* pWaitDstStageMask{};\n    uint32_t commandBufferCount;\n    VkCommandBuffer* pCommandBuffers{};\n    uint32_t signalSemaphoreCount;\n    VkSemaphore* pSignalSemaphores{};\n\n    safe_VkSubmitInfo(const VkSubmitInfo* in_struct, PNextCopyState* copy_state = {}, bool copy_pnext = true);\n    safe_VkSubmitInfo(const safe_VkSubmitInfo& copy_src);\n    safe_VkSubmitInfo& operator=(const safe_VkSubmitInfo& copy_src);\n    safe_VkSubmitInfo();\n    ~safe_VkSubmitInfo();\n    void initialize(const VkSubmitInfo* in_struct, PNextCopyState* copy_state = {});\n    void initialize(const safe_VkSubmitInfo* copy_src, PNextCopyState* copy_state = {});\n    VkSubmitInfo* ptr() { return reinterpret_cast<VkSubmitInfo*>(this); }\n    VkSubmitInfo const* ptr() const { return reinterpret_cast<VkSubmitInfo const*>(this); }\n};\nstruct safe_VkMappedMemoryRange {\n    VkStructureType sType;\n    const void* pNext{};\n    VkDeviceMemory memory;\n    VkDeviceSize offset;\n    VkDeviceSize size;\n\n    safe_VkMappedMemoryRange(const VkMappedMemoryRange* in_struct, PNextCopyState* copy_state = {}, bool copy_pnext = true);\n    safe_VkMappedMemoryRange(const safe_VkMappedMemoryRange& copy_src);\n    safe_VkMappedMemoryRange& operator=(const safe_VkMappedMemoryRange& copy_src);\n    safe_VkMappedMemoryRange();\n    ~safe_VkMappedMemoryRange();\n    void initialize(const VkMappedMemoryRange* in_struct, PNextCopyState* copy_state = {});\n    void initialize(const safe_VkMappedMemoryRange* copy_src, PNextCopyState* copy_state = {});\n    VkMappedMemoryRange* ptr() { return reinterpret_cast<VkMappedMemoryRange*>(this); }\n    VkMappedMemoryRange const* ptr() const { return reinterpret_cast<VkMappedMemoryRange const*>(this); }\n};\nstruct safe_VkMemoryAllocateInfo {\n    VkStructureType sType;\n    const void* pNext{};\n    VkDeviceSize allocationSize;\n    uint32_t memoryTypeIndex;\n\n    safe_VkMemoryAllocateInfo(const VkMemoryAllocateInfo* in_struct, PNextCopyState* copy_state = {}, bool copy_pnext = true);\n    safe_VkMemoryAllocateInfo(const safe_VkMemoryAllocateInfo& copy_src);\n    safe_VkMemoryAllocateInfo& operator=(const safe_VkMemoryAllocateInfo& copy_src);\n    safe_VkMemoryAllocateInfo();\n    ~safe_VkMemoryAllocateInfo();\n    void initialize(const VkMemoryAllocateInfo* in_struct, PNextCopyState* copy_state = {});\n    void initialize(const safe_VkMemoryAllocateInfo* copy_src, PNextCopyState* copy_state = {});\n    VkMemoryAllocateInfo* ptr() { return reinterpret_cast<VkMemoryAllocateInfo*>(this); }\n    VkMemoryAllocateInfo const* ptr() const { return reinterpret_cast<VkMemoryAllocateInfo const*>(this); }\n};\nstruct safe_VkSparseBufferMemoryBindInfo {\n    VkBuffer buffer;\n    uint32_t bindCount;\n    VkSparseMemoryBind* pBinds{};\n\n    safe_VkSparseBufferMemoryBindInfo(const VkSparseBufferMemoryBindInfo* in_struct, PNextCopyState* copy_state = {});\n    safe_VkSparseBufferMemoryBindInfo(const safe_VkSparseBufferMemoryBindInfo& copy_src);\n    safe_VkSparseBufferMemoryBindInfo& operator=(const safe_VkSparseBufferMemoryBindInfo& copy_src);\n    safe_VkSparseBufferMemoryBindInfo();\n    ~safe_VkSparseBufferMemoryBindInfo();\n    void initialize(const VkSparseBufferMemoryBindInfo* in_struct, PNextCopyState* copy_state = {});\n    void initialize(const safe_VkSparseBufferMemoryBindInfo* copy_src, PNextCopyState* copy_state = {});\n    VkSparseBufferMemoryBindInfo* ptr() { return reinterpret_cast<VkSparseBufferMemoryBindInfo*>(this); }\n    VkSparseBufferMemoryBindInfo const* ptr() const { return reinterpret_cast<VkSparseBufferMemoryBindInfo const*>(this); }\n};\nstruct safe_VkSparseImageOpaqueMemoryBindInfo {\n    VkImage image;\n    uint32_t bindCount;\n    VkSparseMemoryBind* pBinds{};\n\n    safe_VkSparseImageOpaqueMemoryBindInfo(const VkSparseImageOpaqueMemoryBindInfo* in_struct, PNextCopyState* copy_state = {});\n    safe_VkSparseImageOpaqueMemoryBindInfo(const safe_VkSparseImageOpaqueMemoryBindInfo& copy_src);\n    safe_VkSparseImageOpaqueMemoryBindInfo& operator=(const safe_VkSparseImageOpaqueMemoryBindInfo& copy_src);\n    safe_VkSparseImageOpaqueMemoryBindInfo();\n    ~safe_VkSparseImageOpaqueMemoryBindInfo();\n    void initialize(const VkSparseImageOpaqueMemoryBindInfo* in_struct, PNextCopyState* copy_state = {});\n    void initialize(const safe_VkSparseImageOpaqueMemoryBindInfo* copy_src, PNextCopyState* copy_state = {});\n    VkSparseImageOpaqueMemoryBindInfo* ptr() { return reinterpret_cast<VkSparseImageOpaqueMemoryBindInfo*>(this); }\n    VkSparseImageOpaqueMemoryBindInfo const* ptr() const {\n        return reinterpret_cast<VkSparseImageOpaqueMemoryBindInfo const*>(this);\n    }\n};\nstruct safe_VkSparseImageMemoryBindInfo {\n    VkImage image;\n    uint32_t bindCount;\n    VkSparseImageMemoryBind* pBinds{};\n\n    safe_VkSparseImageMemoryBindInfo(const VkSparseImageMemoryBindInfo* in_struct, PNextCopyState* copy_state = {});\n    safe_VkSparseImageMemoryBindInfo(const safe_VkSparseImageMemoryBindInfo& copy_src);\n    safe_VkSparseImageMemoryBindInfo& operator=(const safe_VkSparseImageMemoryBindInfo& copy_src);\n    safe_VkSparseImageMemoryBindInfo();\n    ~safe_VkSparseImageMemoryBindInfo();\n    void initialize(const VkSparseImageMemoryBindInfo* in_struct, PNextCopyState* copy_state = {});\n    void initialize(const safe_VkSparseImageMemoryBindInfo* copy_src, PNextCopyState* copy_state = {});\n    VkSparseImageMemoryBindInfo* ptr() { return reinterpret_cast<VkSparseImageMemoryBindInfo*>(this); }\n    VkSparseImageMemoryBindInfo const* ptr() const { return reinterpret_cast<VkSparseImageMemoryBindInfo const*>(this); }\n};\nstruct safe_VkBindSparseInfo {\n    VkStructureType sType;\n    const void* pNext{};\n    uint32_t waitSemaphoreCount;\n    VkSemaphore* pWaitSemaphores{};\n    uint32_t bufferBindCount;\n    safe_VkSparseBufferMemoryBindInfo* pBufferBinds{};\n    uint32_t imageOpaqueBindCount;\n    safe_VkSparseImageOpaqueMemoryBindInfo* pImageOpaqueBinds{};\n    uint32_t imageBindCount;\n    safe_VkSparseImageMemoryBindInfo* pImageBinds{};\n    uint32_t signalSemaphoreCount;\n    VkSemaphore* pSignalSemaphores{};\n\n    safe_VkBindSparseInfo(const VkBindSparseInfo* in_struct, PNextCopyState* copy_state = {}, bool copy_pnext = true);\n    safe_VkBindSparseInfo(const safe_VkBindSparseInfo& copy_src);\n    safe_VkBindSparseInfo& operator=(const safe_VkBindSparseInfo& copy_src);\n    safe_VkBindSparseInfo();\n    ~safe_VkBindSparseInfo();\n    void initialize(const VkBindSparseInfo* in_struct, PNextCopyState* copy_state = {});\n    void initialize(const safe_VkBindSparseInfo* copy_src, PNextCopyState* copy_state = {});\n    VkBindSparseInfo* ptr() { return reinterpret_cast<VkBindSparseInfo*>(this); }\n    VkBindSparseInfo const* ptr() const { return reinterpret_cast<VkBindSparseInfo const*>(this); }\n};\nstruct safe_VkFenceCreateInfo {\n    VkStructureType sType;\n    const void* pNext{};\n    VkFenceCreateFlags flags;\n\n    safe_VkFenceCreateInfo(const VkFenceCreateInfo* in_struct, PNextCopyState* copy_state = {}, bool copy_pnext = true);\n    safe_VkFenceCreateInfo(const safe_VkFenceCreateInfo& copy_src);\n    safe_VkFenceCreateInfo& operator=(const safe_VkFenceCreateInfo& copy_src);\n    safe_VkFenceCreateInfo();\n    ~safe_VkFenceCreateInfo();\n    void initialize(const VkFenceCreateInfo* in_struct, PNextCopyState* copy_state = {});\n    void initialize(const safe_VkFenceCreateInfo* copy_src, PNextCopyState* copy_state = {});\n    VkFenceCreateInfo* ptr() { return reinterpret_cast<VkFenceCreateInfo*>(this); }\n    VkFenceCreateInfo const* ptr() const { return reinterpret_cast<VkFenceCreateInfo const*>(this); }\n};\nstruct safe_VkSemaphoreCreateInfo {\n    VkStructureType sType;\n    const void* pNext{};\n    VkSemaphoreCreateFlags flags;\n\n    safe_VkSemaphoreCreateInfo(const VkSemaphoreCreateInfo* in_struct, PNextCopyState* copy_state = {}, bool copy_pnext = true);\n    safe_VkSemaphoreCreateInfo(const safe_VkSemaphoreCreateInfo& copy_src);\n    safe_VkSemaphoreCreateInfo& operator=(const safe_VkSemaphoreCreateInfo& copy_src);\n    safe_VkSemaphoreCreateInfo();\n    ~safe_VkSemaphoreCreateInfo();\n    void initialize(const VkSemaphoreCreateInfo* in_struct, PNextCopyState* copy_state = {});\n    void initialize(const safe_VkSemaphoreCreateInfo* copy_src, PNextCopyState* copy_state = {});\n    VkSemaphoreCreateInfo* ptr() { return reinterpret_cast<VkSemaphoreCreateInfo*>(this); }\n    VkSemaphoreCreateInfo const* ptr() const { return reinterpret_cast<VkSemaphoreCreateInfo const*>(this); }\n};\nstruct safe_VkQueryPoolCreateInfo {\n    VkStructureType sType;\n    const void* pNext{};\n    VkQueryPoolCreateFlags flags;\n    VkQueryType queryType;\n    uint32_t queryCount;\n    VkQueryPipelineStatisticFlags pipelineStatistics;\n\n    safe_VkQueryPoolCreateInfo(const VkQueryPoolCreateInfo* in_struct, PNextCopyState* copy_state = {}, bool copy_pnext = true);\n    safe_VkQueryPoolCreateInfo(const safe_VkQueryPoolCreateInfo& copy_src);\n    safe_VkQueryPoolCreateInfo& operator=(const safe_VkQueryPoolCreateInfo& copy_src);\n    safe_VkQueryPoolCreateInfo();\n    ~safe_VkQueryPoolCreateInfo();\n    void initialize(const VkQueryPoolCreateInfo* in_struct, PNextCopyState* copy_state = {});\n    void initialize(const safe_VkQueryPoolCreateInfo* copy_src, PNextCopyState* copy_state = {});\n    VkQueryPoolCreateInfo* ptr() { return reinterpret_cast<VkQueryPoolCreateInfo*>(this); }\n    VkQueryPoolCreateInfo const* ptr() const { return reinterpret_cast<VkQueryPoolCreateInfo const*>(this); }\n};\nstruct safe_VkBufferCreateInfo {\n    VkStructureType sType;\n    const void* pNext{};\n    VkBufferCreateFlags flags;\n    VkDeviceSize size;\n    VkBufferUsageFlags usage;\n    VkSharingMode sharingMode;\n    uint32_t queueFamilyIndexCount;\n    const uint32_t* pQueueFamilyIndices{};\n\n    safe_VkBufferCreateInfo(const VkBufferCreateInfo* in_struct, PNextCopyState* copy_state = {}, bool copy_pnext = true);\n    safe_VkBufferCreateInfo(const safe_VkBufferCreateInfo& copy_src);\n    safe_VkBufferCreateInfo& operator=(const safe_VkBufferCreateInfo& copy_src);\n    safe_VkBufferCreateInfo();\n    ~safe_VkBufferCreateInfo();\n    void initialize(const VkBufferCreateInfo* in_struct, PNextCopyState* copy_state = {});\n    void initialize(const safe_VkBufferCreateInfo* copy_src, PNextCopyState* copy_state = {});\n    VkBufferCreateInfo* ptr() { return reinterpret_cast<VkBufferCreateInfo*>(this); }\n    VkBufferCreateInfo const* ptr() const { return reinterpret_cast<VkBufferCreateInfo const*>(this); }\n};\nstruct safe_VkImageCreateInfo {\n    VkStructureType sType;\n    const void* pNext{};\n    VkImageCreateFlags flags;\n    VkImageType imageType;\n    VkFormat format;\n    VkExtent3D extent;\n    uint32_t mipLevels;\n    uint32_t arrayLayers;\n    VkSampleCountFlagBits samples;\n    VkImageTiling tiling;\n    VkImageUsageFlags usage;\n    VkSharingMode sharingMode;\n    uint32_t queueFamilyIndexCount;\n    const uint32_t* pQueueFamilyIndices{};\n    VkImageLayout initialLayout;\n\n    safe_VkImageCreateInfo(const VkImageCreateInfo* in_struct, PNextCopyState* copy_state = {}, bool copy_pnext = true);\n    safe_VkImageCreateInfo(const safe_VkImageCreateInfo& copy_src);\n    safe_VkImageCreateInfo& operator=(const safe_VkImageCreateInfo& copy_src);\n    safe_VkImageCreateInfo();\n    ~safe_VkImageCreateInfo();\n    void initialize(const VkImageCreateInfo* in_struct, PNextCopyState* copy_state = {});\n    void initialize(const safe_VkImageCreateInfo* copy_src, PNextCopyState* copy_state = {});\n    VkImageCreateInfo* ptr() { return reinterpret_cast<VkImageCreateInfo*>(this); }\n    VkImageCreateInfo const* ptr() const { return reinterpret_cast<VkImageCreateInfo const*>(this); }\n};\nstruct safe_VkImageViewCreateInfo {\n    VkStructureType sType;\n    const void* pNext{};\n    VkImageViewCreateFlags flags;\n    VkImage image;\n    VkImageViewType viewType;\n    VkFormat format;\n    VkComponentMapping components;\n    VkImageSubresourceRange subresourceRange;\n\n    safe_VkImageViewCreateInfo(const VkImageViewCreateInfo* in_struct, PNextCopyState* copy_state = {}, bool copy_pnext = true);\n    safe_VkImageViewCreateInfo(const safe_VkImageViewCreateInfo& copy_src);\n    safe_VkImageViewCreateInfo& operator=(const safe_VkImageViewCreateInfo& copy_src);\n    safe_VkImageViewCreateInfo();\n    ~safe_VkImageViewCreateInfo();\n    void initialize(const VkImageViewCreateInfo* in_struct, PNextCopyState* copy_state = {});\n    void initialize(const safe_VkImageViewCreateInfo* copy_src, PNextCopyState* copy_state = {});\n    VkImageViewCreateInfo* ptr() { return reinterpret_cast<VkImageViewCreateInfo*>(this); }\n    VkImageViewCreateInfo const* ptr() const { return reinterpret_cast<VkImageViewCreateInfo const*>(this); }\n};\nstruct safe_VkCommandPoolCreateInfo {\n    VkStructureType sType;\n    const void* pNext{};\n    VkCommandPoolCreateFlags flags;\n    uint32_t queueFamilyIndex;\n\n    safe_VkCommandPoolCreateInfo(const VkCommandPoolCreateInfo* in_struct, PNextCopyState* copy_state = {}, bool copy_pnext = true);\n    safe_VkCommandPoolCreateInfo(const safe_VkCommandPoolCreateInfo& copy_src);\n    safe_VkCommandPoolCreateInfo& operator=(const safe_VkCommandPoolCreateInfo& copy_src);\n    safe_VkCommandPoolCreateInfo();\n    ~safe_VkCommandPoolCreateInfo();\n    void initialize(const VkCommandPoolCreateInfo* in_struct, PNextCopyState* copy_state = {});\n    void initialize(const safe_VkCommandPoolCreateInfo* copy_src, PNextCopyState* copy_state = {});\n    VkCommandPoolCreateInfo* ptr() { return reinterpret_cast<VkCommandPoolCreateInfo*>(this); }\n    VkCommandPoolCreateInfo const* ptr() const { return reinterpret_cast<VkCommandPoolCreateInfo const*>(this); }\n};\nstruct safe_VkCommandBufferAllocateInfo {\n    VkStructureType sType;\n    const void* pNext{};\n    VkCommandPool commandPool;\n    VkCommandBufferLevel level;\n    uint32_t commandBufferCount;\n\n    safe_VkCommandBufferAllocateInfo(const VkCommandBufferAllocateInfo* in_struct, PNextCopyState* copy_state = {},\n                                     bool copy_pnext = true);\n    safe_VkCommandBufferAllocateInfo(const safe_VkCommandBufferAllocateInfo& copy_src);"}